example.py
test_downsampled.py
das2numpy/__init__.py
das2numpy/__main__.py
das2numpy/chunk.py
das2numpy/filefinder.py
das2numpy/test.py
das2numpy/utils.py
das2numpy/setups/light_tdms_reader.py
das2numpy/setups/optasense_b35idefix.py
das2numpy/setups/optasense_b35idefix_fast.py
das2numpy/setups/silixa.py
das2numpy/setups/silixa_200hz.py
das2numpy-0.0.5.dist-info/licenses/LICENSE
das2numpy-0.0.5.dist-info/METADATA
das2numpy-0.0.5.dist-info/WHEEL
das2numpy-0.0.5.dist-info/top_level.txt
das2numpy-0.0.5.dist-info/RECORD
