Metadata-Version: 2.4
Name: das2numpy
Version: 0.0.5
Summary: A simple and universal package for loading large amounts of distributed acoustic sensing (DAS) data.
Author-email: Erik Genthe <erik.genthe@desy.de>
Project-URL: Homepage, https://git.physnet.uni-hamburg.de/wave/das2numpy
Classifier: Programming Language :: Python :: 3
Classifier: License :: OSI Approved :: GNU General Public License v3 (GPLv3)
Classifier: Operating System :: OS Independent
Requires-Python: >=3.8
License-File: LICENSE
Dynamic: license-file
